{
  "parent": "minecraft:moonfabric/nanoheart",
  "criteria": {
    "sevensword": {
      "conditions": {
        "items": [
          {
            "items": "moonfabric:sevensword"
          }
        ]
      },
      "trigger": "minecraft:inventory_changed"
    }
  },
  "display": {
    "description": "seven sword",
    "frame": "challenge",
    "icon": {
      "count": 1,
      "id": "moonfabric:sevensword"
    },
    "title": "We! Nanos!"
  },
  "requirements": [
    [
      "sevensword"
    ]
  ],
  "rewards": {
    "experience": 100
  },
  "sends_telemetry_event": true
}